[
  {
    "id": "mrtmetcjumd330llyue",
    "timestamp": 1785073768000,
    "dateString": "26/7/2026",
    "hh": "20",
    "mm": "49",
    "hall": "10",
    "type": "builder hall"
  },
  {
    "id": "mrtmetd9o6zzvufohsp",
    "timestamp": 1784823586000,
    "dateString": "23/7/2026",
    "hh": "23",
    "mm": "19",
    "hall": "10",
    "type": "builder hall"
  },
  {
    "id": "mrtmetd9n5lmglwwlj9",
    "timestamp": 1784869975000,
    "dateString": "24/7/2026",
    "hh": "12",
    "mm": "12",
    "hall": "10",
    "type": "builder hall"
  },
  {
    "id": "mrtmetd97uh0jpzfqw6",
    "timestamp": 1784796531000,
    "dateString": "23/7/2026",
    "hh": "15",
    "mm": "48",
    "hall": "10",
    "type": "lab"
  },
  {
    "id": "mrtmetd9svmpqcbpnk9",
    "timestamp": 1784667961000,
    "dateString": "22/7/2026",
    "hh": "04",
    "mm": "06",
    "hall": "10",
    "type": "lab"
  },
  {
    "id": "mrtmetda286ut3hfr94",
    "timestamp": 1784637549000,
    "dateString": "21/7/2026",
    "hh": "19",
    "mm": "39",
    "hall": "10",
    "type": "pet"
  },
  {
    "id": "mrtmetda3rvbrvk18ob",
    "timestamp": 1784591974000,
    "dateString": "21/7/2026",
    "hh": "06",
    "mm": "59",
    "hall": "10",
    "type": "speed builder hall"
  },
  {
    "id": "mrtmetdab7nv46p2j1k",
    "timestamp": 1784601008000,
    "dateString": "21/7/2026",
    "hh": "09",
    "mm": "30",
    "hall": "8",
    "type": "builder hall"
  },
  {
    "id": "mrtmetdahqa2qexfet",
    "timestamp": 1784830273000,
    "dateString": "24/7/2026",
    "hh": "01",
    "mm": "11",
    "hall": "8",
    "type": "builder hall"
  },
  {
    "id": "mrtmetda17keq734kv9i",
    "timestamp": 1784911740000,
    "dateString": "24/7/2026",
    "hh": "23",
    "mm": "49",
    "hall": "8",
    "type": "builder hall"
  },
  {
    "id": "mrtmetdapyad1ao09qn",
    "timestamp": 1784645786000,
    "dateString": "21/7/2026",
    "hh": "21",
    "mm": "56",
    "hall": "8",
    "type": "lab"
  },
  {
    "id": "mrtmetdaxae370tqd7c",
    "timestamp": 1784632163000,
    "dateString": "21/7/2026",
    "hh": "18",
    "mm": "09",
    "hall": "8",
    "type": "lab"
  },
  {
    "id": "mrtmetda58vpdpovbc",
    "timestamp": 1784617248000,
    "dateString": "21/7/2026",
    "hh": "14",
    "mm": "00",
    "hall": "8",
    "type": "pet"
  },
  {
    "id": "mrtmetda7ol3oyl9ja5",
    "timestamp": 1784591770000,
    "dateString": "21/7/2026",
    "hh": "06",
    "mm": "56",
    "hall": "8",
    "type": "speed builder hall"
  },
  {
    "id": "mrtmetdbsnokt47dlq",
    "timestamp": 1784683468000,
    "dateString": "22/7/2026",
    "hh": "08",
    "mm": "24",
    "hall": "7",
    "type": "builder hall"
  },
  {
    "id": "mrtmetdbvoojl7cgzz",
    "timestamp": 1784685617000,
    "dateString": "22/7/2026",
    "hh": "09",
    "mm": "00",
    "hall": "7",
    "type": "builder hall"
  },
  {
    "id": "mrtmetdb34p4zcg2e98",
    "timestamp": 1784608297000,
    "dateString": "21/7/2026",
    "hh": "11",
    "mm": "31",
    "hall": "7",
    "type": "builder hall"
  },
  {
    "id": "mrtmetdb6xjgijzrjrt",
    "timestamp": 1784588838000,
    "dateString": "21/7/2026",
    "hh": "06",
    "mm": "07",
    "hall": "7",
    "type": "lab"
  },
  {
    "id": "mrtmetdb1y954ixs5soi",
    "timestamp": 1784673790000,
    "dateString": "22/7/2026",
    "hh": "05",
    "mm": "43",
    "hall": "7",
    "type": "lab"
  },
  {
    "id": "mrtmetdbnyvdegf6x1l",
    "timestamp": 1784613567000,
    "dateString": "21/7/2026",
    "hh": "12",
    "mm": "59",
    "hall": "7",
    "type": "pet"
  },
  {
    "id": "mrtmetdbgqs0gl7bzvf",
    "timestamp": 1784593108000,
    "dateString": "21/7/2026",
    "hh": "07",
    "mm": "18",
    "hall": "7",
    "type": "speed lab"
  },
  {
    "id": "mrtmetdbq3gu4iljoy",
    "timestamp": 1784604086000,
    "dateString": "21/7/2026",
    "hh": "10",
    "mm": "21",
    "hall": "7",
    "type": "speed builder hall"
  },
  {
    "id": "mrtmetdb9faya4fbrpu",
    "timestamp": 1784864456000,
    "dateString": "24/7/2026",
    "hh": "10",
    "mm": "40",
    "hall": "6",
    "type": "builder hall"
  },
  {
    "id": "mrtmetdb12q076fdmhor",
    "timestamp": 1784673265000,
    "dateString": "22/7/2026",
    "hh": "05",
    "mm": "34",
    "hall": "6",
    "type": "builder hall"
  },
  {
    "id": "mrtmetdbq2wn0w68rn",
    "timestamp": 1784843627000,
    "dateString": "24/7/2026",
    "hh": "04",
    "mm": "53",
    "hall": "6",
    "type": "builder hall"
  },
  {
    "id": "mrtmetdbdjzih72rsbp",
    "timestamp": 1784903933000,
    "dateString": "24/7/2026",
    "hh": "21",
    "mm": "38",
    "hall": "6",
    "type": "lab"
  },
  {
    "id": "mrtmetdbmxl6hboxfih",
    "timestamp": 1784632742000,
    "dateString": "21/7/2026",
    "hh": "18",
    "mm": "19",
    "hall": "6",
    "type": "lab"
  },
  {
    "id": "mrtmetdbqlhnaex4b3e",
    "timestamp": 1784633380000,
    "dateString": "21/7/2026",
    "hh": "18",
    "mm": "29",
    "hall": "6",
    "type": "pet"
  },
  {
    "id": "mrtmetdbb95d2u76v7s",
    "timestamp": 1784638129000,
    "dateString": "21/7/2026",
    "hh": "19",
    "mm": "48",
    "hall": "6",
    "type": "speed builder hall"
  },
  {
    "id": "mrtmetdb34w2m1hdn87",
    "timestamp": 1784708102000,
    "dateString": "22/7/2026",
    "hh": "15",
    "mm": "15",
    "hall": "5",
    "type": "builder hall"
  },
  {
    "id": "mrtmetdb2d7omk1x1wl",
    "timestamp": 1784781548000,
    "dateString": "23/7/2026",
    "hh": "11",
    "mm": "39",
    "hall": "5",
    "type": "builder hall"
  },
  {
    "id": "mrtmetdbm9dhb7bpmpr",
    "timestamp": 1784850418000,
    "dateString": "24/7/2026",
    "hh": "06",
    "mm": "46",
    "hall": "5",
    "type": "builder hall"
  },
  {
    "id": "mrtmetdbo7q1g70m7aj",
    "timestamp": 1784626321000,
    "dateString": "21/7/2026",
    "hh": "16",
    "mm": "32",
    "hall": "5",
    "type": "lab"
  },
  {
    "id": "mrtmetdb4ezun6lw7ch",
    "timestamp": 1784598558000,
    "dateString": "21/7/2026",
    "hh": "08",
    "mm": "49",
    "hall": "5",
    "type": "lab"
  },
  {
    "id": "mrtmetdbsl21w8trub",
    "timestamp": 1784638881000,
    "dateString": "21/7/2026",
    "hh": "20",
    "mm": "01",
    "hall": "5",
    "type": "pet"
  },
  {
    "id": "mrtmetdbwmxl2viri9o",
    "timestamp": 1784591959000,
    "dateString": "21/7/2026",
    "hh": "06",
    "mm": "59",
    "hall": "5",
    "type": "speed builder hall"
  },
  {
    "id": "mrtmetdbg1mx7m4yevj",
    "timestamp": 1784660758000,
    "dateString": "22/7/2026",
    "hh": "02",
    "mm": "05",
    "hall": "4",
    "type": "builder hall"
  },
  {
    "id": "mrtmetdbveye04phbki",
    "timestamp": 1784695266000,
    "dateString": "22/7/2026",
    "hh": "11",
    "mm": "41",
    "hall": "4",
    "type": "builder hall"
  },
  {
    "id": "mrtmetdb0os1coq1s1uc",
    "timestamp": 1784851521000,
    "dateString": "24/7/2026",
    "hh": "07",
    "mm": "05",
    "hall": "4",
    "type": "builder hall"
  },
  {
    "id": "mrtmetdbkqs6g6y94nn",
    "timestamp": 1784902452000,
    "dateString": "24/7/2026",
    "hh": "21",
    "mm": "14",
    "hall": "4",
    "type": "lab"
  },
  {
    "id": "mrtmetdbby8bfm5ggkh",
    "timestamp": 1784639644000,
    "dateString": "21/7/2026",
    "hh": "20",
    "mm": "14",
    "hall": "4",
    "type": "lab"
  },
  {
    "id": "mrtmetdbwdm38iicf2g",
    "timestamp": 1784633529000,
    "dateString": "21/7/2026",
    "hh": "18",
    "mm": "32",
    "hall": "4",
    "type": "pet"
  },
  {
    "id": "mrtmetdblg79kysm4oh",
    "timestamp": 1784591818000,
    "dateString": "21/7/2026",
    "hh": "06",
    "mm": "56",
    "hall": "4",
    "type": "speed builder hall"
  },
  {
    "id": "mrtmetdbot4y33cn06p",
    "timestamp": 1784767490000,
    "dateString": "23/7/2026",
    "hh": "07",
    "mm": "44",
    "hall": "3",
    "type": "builder hall"
  },
  {
    "id": "mrtmetdba5xhrl6qbd8",
    "timestamp": 1784623275000,
    "dateString": "21/7/2026",
    "hh": "15",
    "mm": "41",
    "hall": "3",
    "type": "builder hall"
  },
  {
    "id": "mrtmetdbc4c0qk000c8",
    "timestamp": 1784928198000,
    "dateString": "25/7/2026",
    "hh": "04",
    "mm": "23",
    "hall": "3",
    "type": "builder hall"
  },
  {
    "id": "mrtmetdbnjp1n8ih36m",
    "timestamp": 1784856146000,
    "dateString": "24/7/2026",
    "hh": "08",
    "mm": "22",
    "hall": "3",
    "type": "lab"
  },
  {
    "id": "mrtmetdbjb0m0pqehm",
    "timestamp": 1784626390000,
    "dateString": "21/7/2026",
    "hh": "16",
    "mm": "33",
    "hall": "3",
    "type": "lab"
  },
  {
    "id": "mrtmetdbs1y8nmsjxm",
    "timestamp": 1784710781000,
    "dateString": "22/7/2026",
    "hh": "15",
    "mm": "59",
    "hall": "3",
    "type": "pet"
  },
  {
    "id": "mrtmetdbeqsdhy665f",
    "timestamp": 1784601205000,
    "dateString": "21/7/2026",
    "hh": "09",
    "mm": "33",
    "hall": "3",
    "type": "speed builder hall"
  },
  {
    "id": "mrtmetdc92ilnzbcezp",
    "timestamp": 1784958054000,
    "dateString": "25/7/2026",
    "hh": "12",
    "mm": "40",
    "hall": "2",
    "type": "builder hall"
  },
  {
    "id": "mrtmetdc6d342el9sfn",
    "timestamp": 1784632925000,
    "dateString": "21/7/2026",
    "hh": "18",
    "mm": "22",
    "hall": "2",
    "type": "builder hall"
  },
  {
    "id": "mrtmetdc6s52jg7oa23",
    "timestamp": 1784781223000,
    "dateString": "23/7/2026",
    "hh": "11",
    "mm": "33",
    "hall": "2",
    "type": "builder hall"
  },
  {
    "id": "mrtmetdc4v9afgqz1mq",
    "timestamp": 1784641263000,
    "dateString": "21/7/2026",
    "hh": "20",
    "mm": "41",
    "hall": "2",
    "type": "lab"
  },
  {
    "id": "mrtmetdc5wc40vtvsbe",
    "timestamp": 1784607919000,
    "dateString": "21/7/2026",
    "hh": "11",
    "mm": "25",
    "hall": "2",
    "type": "lab"
  },
  {
    "id": "mrtmetdc239jmdn6rqq",
    "timestamp": 1784609872000,
    "dateString": "21/7/2026",
    "hh": "11",
    "mm": "57",
    "hall": "2",
    "type": "pet"
  },
  {
    "id": "mrtmetdcr11wipcjiz",
    "timestamp": 1784593507000,
    "dateString": "21/7/2026",
    "hh": "07",
    "mm": "25",
    "hall": "2",
    "type": "speed lab"
  },
  {
    "id": "mrtmetdcfzzizdgabda",
    "timestamp": 1784592071000,
    "dateString": "21/7/2026",
    "hh": "07",
    "mm": "01",
    "hall": "2",
    "type": "speed builder hall"
  },
  {
    "id": "mrtmetdcxh466xnmydq",
    "timestamp": 1784589954000,
    "dateString": "21/7/2026",
    "hh": "06",
    "mm": "25",
    "hall": "1",
    "type": "builder hall"
  },
  {
    "id": "mrtmetdc3173boi41ri",
    "timestamp": 1784873407000,
    "dateString": "24/7/2026",
    "hh": "13",
    "mm": "10",
    "hall": "1",
    "type": "builder hall"
  },
  {
    "id": "mrtmetdcisueglysky",
    "timestamp": 1784912424000,
    "dateString": "25/7/2026",
    "hh": "00",
    "mm": "00",
    "hall": "1",
    "type": "builder hall"
  },
  {
    "id": "mrtmetdclymmw6kc5h",
    "timestamp": 1784650389000,
    "dateString": "21/7/2026",
    "hh": "23",
    "mm": "13",
    "hall": "1",
    "type": "lab"
  },
  {
    "id": "mrtmetdccuw4obbp94p",
    "timestamp": 1784672081000,
    "dateString": "22/7/2026",
    "hh": "05",
    "mm": "14",
    "hall": "1",
    "type": "lab"
  },
  {
    "id": "mrtmetdcmyhc6410foh",
    "timestamp": 1784617239000,
    "dateString": "21/7/2026",
    "hh": "14",
    "mm": "00",
    "hall": "1",
    "type": "pet"
  },
  {
    "id": "mrtmetdc7m2rdx3u2we",
    "timestamp": 1784638137000,
    "dateString": "21/7/2026",
    "hh": "19",
    "mm": "48",
    "hall": "1",
    "type": "speed builder hall"
  },
  {
    "id": "mrtnalj9shbilr6paae",
    "timestamp": 1784662725000,
    "dateString": "22/7/2026",
    "hh": "02",
    "mm": "38",
    "hall": "9",
    "type": "builder hall"
  },
  {
    "id": "mrtnalk3he8smn8dw19",
    "timestamp": 1784754236000,
    "dateString": "23/7/2026",
    "hh": "04",
    "mm": "03",
    "hall": "9",
    "type": "builder hall"
  },
  {
    "id": "mrtnalk37buushoozxq",
    "timestamp": 1784668125000,
    "dateString": "22/7/2026",
    "hh": "04",
    "mm": "08",
    "hall": "9",
    "type": "builder hall"
  },
  {
    "id": "mrtnalk3sdp8ydlzioe",
    "timestamp": 1784788563000,
    "dateString": "23/7/2026",
    "hh": "13",
    "mm": "36",
    "hall": "9",
    "type": "lab"
  },
  {
    "id": "mrtnalk38mn1f6kofak",
    "timestamp": 1784616369000,
    "dateString": "21/7/2026",
    "hh": "13",
    "mm": "46",
    "hall": "9",
    "type": "lab"
  },
  {
    "id": "mrtnalk3x5w8diamj1",
    "timestamp": 1784591530000,
    "dateString": "21/7/2026",
    "hh": "06",
    "mm": "52",
    "hall": "9",
    "type": "pet"
  },
  {
    "id": "mrtnalk3r5zlz11gu58",
    "timestamp": 1784591737000,
    "dateString": "21/7/2026",
    "hh": "06",
    "mm": "55",
    "hall": "9",
    "type": "speed builder hall"
  }
]