[
  {
    "id": "mppv4f109xwjovh05pa",
    "timestamp": 1780160637108,
    "dateString": "31/5/2026",
    "hh": "00",
    "mm": "03",
    "type": "lab",
    "hall": "4"
  },
  {
    "id": "mpqgrm04n7cpt9wcnbh",
    "timestamp": 1780279791167,
    "dateString": "1/6/2026",
    "hh": "09",
    "mm": "09",
    "type": "lab",
    "hall": "8"
  },
  {
    "id": "mpqnr1r2hdiue1kk85p",
    "timestamp": 1780291522237,
    "dateString": "1/6/2026",
    "hh": "12",
    "mm": "25",
    "type": "lab",
    "hall": "9"
  },
  {
    "id": "mpqu59xidzk2ypq46zq",
    "timestamp": 1780302263711,
    "dateString": "1/6/2026",
    "hh": "15",
    "mm": "24",
    "type": "lab",
    "hall": "3"
  },
  {
    "id": "mprbb9g0y4lcv68f23",
    "timestamp": 1780157996496,
    "dateString": "30/5/2026",
    "hh": "23",
    "mm": "19",
    "type": "lab",
    "hall": "10"
  },
  {
    "id": "mprlwczs67efr1pdxf",
    "timestamp": 1780171217032,
    "dateString": "31/5/2026",
    "hh": "03",
    "mm": "00",
    "type": "speed builder hall",
    "hall": "6"
  },
  {
    "id": "mprr0xc7756io01a43c",
    "timestamp": 1780172028103,
    "dateString": "31/5/2026",
    "hh": "03",
    "mm": "13",
    "type": "speed builder hall",
    "hall": "1"
  },
  {
    "id": "mprr2jjmhe4tg6xq3gh",
    "timestamp": 1780172283538,
    "dateString": "31/5/2026",
    "hh": "03",
    "mm": "18",
    "type": "speed builder hall",
    "hall": "2"
  },
  {
    "id": "mprvfxpto3vy0muwbh",
    "timestamp": 1780282106896,
    "dateString": "1/6/2026",
    "hh": "09",
    "mm": "48",
    "type": "lab",
    "hall": "7"
  },
  {
    "id": "mps2td8qywb9th7mi5",
    "timestamp": 1780207550858,
    "dateString": "31/5/2026",
    "hh": "13",
    "mm": "05",
    "type": "speed builder hall",
    "hall": "7"
  },
  {
    "id": "mps6bp12el0xdo4u1f",
    "timestamp": 1780300384790,
    "dateString": "1/6/2026",
    "hh": "14",
    "mm": "53",
    "type": "lab",
    "hall": "2"
  },
  {
    "id": "mps6ia3uwypfgrzyael",
    "timestamp": 1780156692040,
    "dateString": "30/5/2026",
    "hh": "22",
    "mm": "58",
    "type": "builder hall",
    "hall": "6"
  },
  {
    "id": "mps6jbq4jr2vzhdyihb",
    "timestamp": 1780304280796,
    "dateString": "1/6/2026",
    "hh": "15",
    "mm": "58",
    "type": "lab",
    "hall": "6"
  },
  {
    "id": "mps6lf0s5k0hgnn8cks",
    "timestamp": 1780300838380,
    "dateString": "1/6/2026",
    "hh": "15",
    "mm": "00",
    "type": "lab",
    "hall": "5"
  },
  {
    "id": "mps6oect3vhf9s1x0lh",
    "timestamp": 1780156977485,
    "dateString": "30/5/2026",
    "hh": "23",
    "mm": "02",
    "type": "builder hall",
    "hall": "3"
  },
  {
    "id": "mps79bso1f2ohz1573z",
    "timestamp": 1780157953942,
    "dateString": "30/5/2026",
    "hh": "23",
    "mm": "19",
    "type": "builder hall",
    "hall": "1"
  },
  {
    "id": "mpsa2mrzw6aerh1c8kk",
    "timestamp": 1780162380431,
    "dateString": "31/5/2026",
    "hh": "00",
    "mm": "33",
    "type": "builder hall",
    "hall": "7"
  },
  {
    "id": "mpsaklzly3266ugktxc",
    "timestamp": 1780221059215,
    "dateString": "31/5/2026",
    "hh": "16",
    "mm": "50",
    "type": "speed builder hall",
    "hall": "8"
  },
  {
    "id": "mpsakv5e55qcn8r4i8y",
    "timestamp": 1780202171090,
    "dateString": "31/5/2026",
    "hh": "11",
    "mm": "36",
    "type": "builder hall",
    "hall": "8"
  },
  {
    "id": "mpsaljsm3p1a0s0nkdd",
    "timestamp": 1780220503030,
    "dateString": "31/5/2026",
    "hh": "16",
    "mm": "41",
    "type": "speed builder hall",
    "hall": "9"
  },
  {
    "id": "mpsaltg6c1bg2rv4d8u",
    "timestamp": 1780153555542,
    "dateString": "30/5/2026",
    "hh": "22",
    "mm": "05",
    "type": "builder hall",
    "hall": "9"
  },
  {
    "id": "mpsg41pawb9l8758cg",
    "timestamp": 1780170424126,
    "dateString": "31/5/2026",
    "hh": "02",
    "mm": "47",
    "type": "speed builder hall",
    "hall": "4"
  },
  {
    "id": "mpsg4n05kgul7hg7ys",
    "timestamp": 1780229431733,
    "dateString": "31/5/2026",
    "hh": "19",
    "mm": "10",
    "type": "speed builder hall",
    "hall": "5"
  },
  {
    "id": "mpsg4vlzglv1barjhic",
    "timestamp": 1780179822887,
    "dateString": "31/5/2026",
    "hh": "05",
    "mm": "23",
    "type": "builder hall",
    "hall": "5"
  },
  {
    "id": "mpsg5mta5zu1nguxbx",
    "timestamp": 1780229658142,
    "dateString": "31/5/2026",
    "hh": "19",
    "mm": "14",
    "type": "speed builder hall",
    "hall": "10"
  },
  {
    "id": "mpsg61kjcp99si3u9mh",
    "timestamp": 1780155997266,
    "dateString": "30/5/2026",
    "hh": "22",
    "mm": "46",
    "type": "builder hall",
    "hall": "10"
  },
  {
    "id": "mpsg77rc6628grjcs1",
    "timestamp": 1780154791944,
    "dateString": "30/5/2026",
    "hh": "22",
    "mm": "26",
    "type": "builder hall",
    "hall": "2"
  },
  {
    "id": "mpsh24b8o1qfpn6jccj",
    "timestamp": 1780156413810,
    "dateString": "30/5/2026",
    "hh": "22",
    "mm": "53",
    "type": "lab",
    "hall": "1"
  },
  {
    "id": "mpsh6jxshty9txigacj",
    "timestamp": 1780231140687,
    "dateString": "31/5/2026",
    "hh": "19",
    "mm": "39",
    "type": "speed builder hall",
    "hall": "3"
  },
  {
    "id": "mpsh6ot0tkkab3xalc",
    "timestamp": 1780187286996,
    "dateString": "31/5/2026",
    "hh": "07",
    "mm": "28",
    "type": "builder hall",
    "hall": "3"
  }
]