[
  {
    "id": "mrylx2orwoq6s3r38rh",
    "timestamp": 1784889343000,
    "dateString": "24/7/2026",
    "hh": "17",
    "mm": "35",
    "hall": "10",
    "type": "normal"
  },
  {
    "id": "mrylx2pwu8smmipd3he",
    "timestamp": 1784905318000,
    "dateString": "24/7/2026",
    "hh": "22",
    "mm": "01",
    "hall": "10",
    "type": "normal"
  },
  {
    "id": "mrylx2pwlshygbsgvbl",
    "timestamp": 1784888043000,
    "dateString": "24/7/2026",
    "hh": "17",
    "mm": "14",
    "hall": "10",
    "type": "normal"
  },
  {
    "id": "mrylx2pw43ebioc4aw",
    "timestamp": 1784913837000,
    "dateString": "25/7/2026",
    "hh": "00",
    "mm": "23",
    "hall": "10",
    "type": "normal"
  },
  {
    "id": "mrylx2pwfpw7d5pvj36",
    "timestamp": 1784905401000,
    "dateString": "24/7/2026",
    "hh": "22",
    "mm": "03",
    "hall": "10",
    "type": "normal"
  },
  {
    "id": "mrylx2pw0nzf5f0k60u",
    "timestamp": 1784909114000,
    "dateString": "24/7/2026",
    "hh": "23",
    "mm": "05",
    "hall": "10",
    "type": "normal"
  },
  {
    "id": "mrylx2pxat6jb417qj7",
    "timestamp": 1785074368000,
    "dateString": "26/7/2026",
    "hh": "20",
    "mm": "59",
    "hall": "10",
    "type": "builder hall"
  },
  {
    "id": "mrylx2px9zohd70we6e",
    "timestamp": 1785110544000,
    "dateString": "27/7/2026",
    "hh": "07",
    "mm": "02",
    "hall": "10",
    "type": "builder hall"
  },
  {
    "id": "mrylx2pxh3sfemvqei",
    "timestamp": 1785270314000,
    "dateString": "29/7/2026",
    "hh": "03",
    "mm": "25",
    "hall": "10",
    "type": "builder hall"
  },
  {
    "id": "mrylx2pxhgrxjuvy6hl",
    "timestamp": 1785261900000,
    "dateString": "29/7/2026",
    "hh": "01",
    "mm": "05",
    "hall": "10",
    "type": "lab"
  },
  {
    "id": "mrylx2pxqkszj8benpi",
    "timestamp": 1784887503000,
    "dateString": "24/7/2026",
    "hh": "17",
    "mm": "05",
    "hall": "10",
    "type": "lab"
  },
  {
    "id": "mrylx2pxnrjd8ua9adr",
    "timestamp": 1785098440000,
    "dateString": "27/7/2026",
    "hh": "03",
    "mm": "40",
    "hall": "10",
    "type": "pet"
  },
  {
    "id": "mrylx2pxoiei6fwreqf",
    "timestamp": 1784935496000,
    "dateString": "25/7/2026",
    "hh": "06",
    "mm": "24",
    "hall": "10",
    "type": "speed lab"
  },
  {
    "id": "mrylx2px9w5t9flxdh4",
    "timestamp": 1784935541000,
    "dateString": "25/7/2026",
    "hh": "06",
    "mm": "25",
    "hall": "10",
    "type": "speed builder hall"
  },
  {
    "id": "mrylx2pxt8h329weo1g",
    "timestamp": 1784905304000,
    "dateString": "24/7/2026",
    "hh": "22",
    "mm": "01",
    "hall": "9",
    "type": "normal"
  },
  {
    "id": "mrylx2pxscnbcy98a",
    "timestamp": 1784905842000,
    "dateString": "24/7/2026",
    "hh": "22",
    "mm": "10",
    "hall": "9",
    "type": "normal"
  },
  {
    "id": "mrylx2pxdren8bllkpk",
    "timestamp": 1784926746000,
    "dateString": "25/7/2026",
    "hh": "03",
    "mm": "59",
    "hall": "9",
    "type": "normal"
  },
  {
    "id": "mrylx2px84eo4tq9axp",
    "timestamp": 1784888851000,
    "dateString": "24/7/2026",
    "hh": "17",
    "mm": "27",
    "hall": "9",
    "type": "normal"
  },
  {
    "id": "mrylx2pxnpc74yalt3f",
    "timestamp": 1784919985000,
    "dateString": "25/7/2026",
    "hh": "02",
    "mm": "06",
    "hall": "9",
    "type": "normal"
  },
  {
    "id": "mrylx2px48jpam0fw2d",
    "timestamp": 1784932718000,
    "dateString": "25/7/2026",
    "hh": "05",
    "mm": "38",
    "hall": "9",
    "type": "normal"
  },
  {
    "id": "mrylx2pxtjmi0ce0h6p",
    "timestamp": 1784974142000,
    "dateString": "25/7/2026",
    "hh": "17",
    "mm": "09",
    "hall": "9",
    "type": "builder hall"
  },
  {
    "id": "mrylx2pxb4ijch2eeu",
    "timestamp": 1785025186000,
    "dateString": "26/7/2026",
    "hh": "07",
    "mm": "19",
    "hall": "9",
    "type": "builder hall"
  },
  {
    "id": "mrylx2px2lvaq1x0ahc",
    "timestamp": 1785118448000,
    "dateString": "27/7/2026",
    "hh": "09",
    "mm": "14",
    "hall": "9",
    "type": "builder hall"
  },
  {
    "id": "mrylx2pyuef7nibdo9",
    "timestamp": 1785108563000,
    "dateString": "27/7/2026",
    "hh": "06",
    "mm": "29",
    "hall": "9",
    "type": "lab"
  },
  {
    "id": "mrylx2pyr3apttb8c1",
    "timestamp": 1784885492000,
    "dateString": "24/7/2026",
    "hh": "16",
    "mm": "31",
    "hall": "9",
    "type": "lab"
  },
  {
    "id": "mrylx2pyqofr87n97a",
    "timestamp": 1785038384000,
    "dateString": "26/7/2026",
    "hh": "10",
    "mm": "59",
    "hall": "9",
    "type": "pet"
  },
  {
    "id": "mrylx2py28tm13dtxa2",
    "timestamp": 1784935142000,
    "dateString": "25/7/2026",
    "hh": "06",
    "mm": "19",
    "hall": "9",
    "type": "speed builder hall"
  },
  {
    "id": "mrylx2pyjwczrwb5rfm",
    "timestamp": 1784884684000,
    "dateString": "24/7/2026",
    "hh": "16",
    "mm": "18",
    "hall": "8",
    "type": "normal"
  },
  {
    "id": "mrylx2py24in5pu49l3",
    "timestamp": 1784884849000,
    "dateString": "24/7/2026",
    "hh": "16",
    "mm": "20",
    "hall": "8",
    "type": "normal"
  },
  {
    "id": "mrylx2py8kp4s4xim7x",
    "timestamp": 1784911552000,
    "dateString": "24/7/2026",
    "hh": "23",
    "mm": "45",
    "hall": "8",
    "type": "normal"
  },
  {
    "id": "mrylx2py8jnj48s0y45",
    "timestamp": 1784948485000,
    "dateString": "25/7/2026",
    "hh": "10",
    "mm": "01",
    "hall": "8",
    "type": "normal"
  },
  {
    "id": "mrylx2pyy4dfqjxixtk",
    "timestamp": 1784920040000,
    "dateString": "25/7/2026",
    "hh": "02",
    "mm": "07",
    "hall": "8",
    "type": "normal"
  },
  {
    "id": "mrylx2pysue1g35lwnb",
    "timestamp": 1784956435000,
    "dateString": "25/7/2026",
    "hh": "12",
    "mm": "13",
    "hall": "8",
    "type": "normal"
  },
  {
    "id": "mrylx2pysu17b91hda",
    "timestamp": 1785044587000,
    "dateString": "26/7/2026",
    "hh": "12",
    "mm": "43",
    "hall": "8",
    "type": "builder hall"
  },
  {
    "id": "mrylx2pynbzrz0bifbb",
    "timestamp": 1785117121000,
    "dateString": "27/7/2026",
    "hh": "08",
    "mm": "52",
    "hall": "8",
    "type": "builder hall"
  },
  {
    "id": "mrylx2pyqosn6srka1",
    "timestamp": 1784926844000,
    "dateString": "25/7/2026",
    "hh": "04",
    "mm": "00",
    "hall": "8",
    "type": "builder hall"
  },
  {
    "id": "mrylx2pyoby0c1uig2",
    "timestamp": 1785175788000,
    "dateString": "28/7/2026",
    "hh": "01",
    "mm": "09",
    "hall": "8",
    "type": "lab"
  },
  {
    "id": "mrylx2py9ilr251s2x",
    "timestamp": 1784966680000,
    "dateString": "25/7/2026",
    "hh": "15",
    "mm": "04",
    "hall": "8",
    "type": "lab"
  },
  {
    "id": "mrylx2py4wkeuozzi1o",
    "timestamp": 1785077972000,
    "dateString": "26/7/2026",
    "hh": "21",
    "mm": "59",
    "hall": "8",
    "type": "pet"
  },
  {
    "id": "mrylx2pyu68946278or",
    "timestamp": 1784935380000,
    "dateString": "25/7/2026",
    "hh": "06",
    "mm": "23",
    "hall": "8",
    "type": "speed builder hall"
  },
  {
    "id": "mrylx2pyg3vfq0jaoql",
    "timestamp": 1784925130000,
    "dateString": "25/7/2026",
    "hh": "03",
    "mm": "32",
    "hall": "7",
    "type": "normal"
  },
  {
    "id": "mrylx2pyzapubgyw81e",
    "timestamp": 1784905345000,
    "dateString": "24/7/2026",
    "hh": "22",
    "mm": "02",
    "hall": "7",
    "type": "normal"
  },
  {
    "id": "mrylx2py5or9tr5t87c",
    "timestamp": 1784886114000,
    "dateString": "24/7/2026",
    "hh": "16",
    "mm": "41",
    "hall": "7",
    "type": "normal"
  },
  {
    "id": "mrylx2pyrnyg8jdd7z",
    "timestamp": 1784931185000,
    "dateString": "25/7/2026",
    "hh": "05",
    "mm": "13",
    "hall": "7",
    "type": "normal"
  },
  {
    "id": "mrylx2py8jjmpkvzl5c",
    "timestamp": 1784911373000,
    "dateString": "24/7/2026",
    "hh": "23",
    "mm": "42",
    "hall": "7",
    "type": "normal"
  },
  {
    "id": "mrylx2pyqazm3d5m3r",
    "timestamp": 1784952107000,
    "dateString": "25/7/2026",
    "hh": "11",
    "mm": "01",
    "hall": "7",
    "type": "normal"
  },
  {
    "id": "mrylx2py04x5hyce2o5",
    "timestamp": 1784968636000,
    "dateString": "25/7/2026",
    "hh": "15",
    "mm": "37",
    "hall": "7",
    "type": "builder hall"
  },
  {
    "id": "mrylx2pyyd6thw8aex",
    "timestamp": 1785040234000,
    "dateString": "26/7/2026",
    "hh": "11",
    "mm": "30",
    "hall": "7",
    "type": "builder hall"
  },
  {
    "id": "mrylx2pyjlctqlxxznb",
    "timestamp": 1785036100000,
    "dateString": "26/7/2026",
    "hh": "10",
    "mm": "21",
    "hall": "7",
    "type": "builder hall"
  },
  {
    "id": "mrylx2pyfgqu0wploxe",
    "timestamp": 1785081869000,
    "dateString": "26/7/2026",
    "hh": "23",
    "mm": "04",
    "hall": "7",
    "type": "lab"
  },
  {
    "id": "mrylx2pyj3cdl3jx1x",
    "timestamp": 1785054673000,
    "dateString": "26/7/2026",
    "hh": "15",
    "mm": "31",
    "hall": "7",
    "type": "lab"
  },
  {
    "id": "mrylx2pyr8fw68hs1r",
    "timestamp": 1785146449000,
    "dateString": "27/7/2026",
    "hh": "17",
    "mm": "00",
    "hall": "7",
    "type": "pet"
  },
  {
    "id": "mrylx2py9e7grr5ngiv",
    "timestamp": 1784935336000,
    "dateString": "25/7/2026",
    "hh": "06",
    "mm": "22",
    "hall": "7",
    "type": "speed builder hall"
  },
  {
    "id": "mrylx2pyvvbi595u3xn",
    "timestamp": 1784924280000,
    "dateString": "25/7/2026",
    "hh": "03",
    "mm": "18",
    "hall": "6",
    "type": "normal"
  },
  {
    "id": "mrylx2pyjezirffbd7",
    "timestamp": 1784888762000,
    "dateString": "24/7/2026",
    "hh": "17",
    "mm": "26",
    "hall": "6",
    "type": "normal"
  },
  {
    "id": "mrylx2pyxcsbj0ni7kc",
    "timestamp": 1784899041000,
    "dateString": "24/7/2026",
    "hh": "20",
    "mm": "17",
    "hall": "6",
    "type": "normal"
  },
  {
    "id": "mrylx2py7affnz1wak9",
    "timestamp": 1784888793000,
    "dateString": "24/7/2026",
    "hh": "17",
    "mm": "26",
    "hall": "6",
    "type": "normal"
  },
  {
    "id": "mrylx2pybffmbekzeun",
    "timestamp": 1784905360000,
    "dateString": "24/7/2026",
    "hh": "22",
    "mm": "02",
    "hall": "6",
    "type": "normal"
  },
  {
    "id": "mrylx2pz5iggceqtbd5",
    "timestamp": 1784903512000,
    "dateString": "24/7/2026",
    "hh": "21",
    "mm": "31",
    "hall": "6",
    "type": "normal"
  },
  {
    "id": "mrylx2pzsjz6kktlajn",
    "timestamp": 1784970348000,
    "dateString": "25/7/2026",
    "hh": "16",
    "mm": "05",
    "hall": "6",
    "type": "builder hall"
  },
  {
    "id": "mrylx2pz2e0rjc5wlks",
    "timestamp": 1785151400000,
    "dateString": "27/7/2026",
    "hh": "18",
    "mm": "23",
    "hall": "6",
    "type": "builder hall"
  },
  {
    "id": "mrylx2pzv2e3zo4szp",
    "timestamp": 1785284101000,
    "dateString": "29/7/2026",
    "hh": "07",
    "mm": "15",
    "hall": "6",
    "type": "builder hall"
  },
  {
    "id": "mrylx2pz4n7y0lb28s",
    "timestamp": 1785063786000,
    "dateString": "26/7/2026",
    "hh": "18",
    "mm": "03",
    "hall": "6",
    "type": "lab"
  },
  {
    "id": "mrylx2pzhi8ry2men4s",
    "timestamp": 1784990431000,
    "dateString": "25/7/2026",
    "hh": "21",
    "mm": "40",
    "hall": "6",
    "type": "lab"
  },
  {
    "id": "mrylx2pzzo00hkie4ie",
    "timestamp": 1785011475000,
    "dateString": "26/7/2026",
    "hh": "03",
    "mm": "31",
    "hall": "6",
    "type": "pet"
  },
  {
    "id": "mrylx2pz3gcrt4y7az",
    "timestamp": 1784883259000,
    "dateString": "24/7/2026",
    "hh": "15",
    "mm": "54",
    "hall": "6",
    "type": "speed builder hall"
  },
  {
    "id": "mrylx2pzcs6qf26umc8",
    "timestamp": 1784920402000,
    "dateString": "25/7/2026",
    "hh": "02",
    "mm": "13",
    "hall": "5",
    "type": "normal"
  },
  {
    "id": "mrylx2pzr0b75n0e5e",
    "timestamp": 1784896595000,
    "dateString": "24/7/2026",
    "hh": "19",
    "mm": "36",
    "hall": "5",
    "type": "normal"
  },
  {
    "id": "mrylx2pz7gg5jbdtey3",
    "timestamp": 1784923678000,
    "dateString": "25/7/2026",
    "hh": "03",
    "mm": "07",
    "hall": "5",
    "type": "normal"
  },
  {
    "id": "mrylx2pz9jci0u5kp98",
    "timestamp": 1784913992000,
    "dateString": "25/7/2026",
    "hh": "00",
    "mm": "26",
    "hall": "5",
    "type": "normal"
  },
  {
    "id": "mrylx2pzosz7na4mcnm",
    "timestamp": 1784922658000,
    "dateString": "25/7/2026",
    "hh": "02",
    "mm": "50",
    "hall": "5",
    "type": "normal"
  },
  {
    "id": "mrylx2pz9w6ddjhibac",
    "timestamp": 1784952223000,
    "dateString": "25/7/2026",
    "hh": "11",
    "mm": "03",
    "hall": "5",
    "type": "normal"
  },
  {
    "id": "mrylx2pzqdpi9yhvkza",
    "timestamp": 1784939163000,
    "dateString": "25/7/2026",
    "hh": "07",
    "mm": "26",
    "hall": "5",
    "type": "builder hall"
  },
  {
    "id": "mrylx2pzcg0w7xax1v",
    "timestamp": 1785005328000,
    "dateString": "26/7/2026",
    "hh": "01",
    "mm": "48",
    "hall": "5",
    "type": "builder hall"
  },
  {
    "id": "mrylx2pz3qinto78oyl",
    "timestamp": 1785250973000,
    "dateString": "28/7/2026",
    "hh": "22",
    "mm": "02",
    "hall": "5",
    "type": "builder hall"
  },
  {
    "id": "mrylx2pzq65ara45qq",
    "timestamp": 1785197049000,
    "dateString": "28/7/2026",
    "hh": "07",
    "mm": "04",
    "hall": "5",
    "type": "lab"
  },
  {
    "id": "mrylx2pz4xq1vwyes5",
    "timestamp": 1784880244000,
    "dateString": "24/7/2026",
    "hh": "15",
    "mm": "04",
    "hall": "5",
    "type": "lab"
  },
  {
    "id": "mrylx2pz28hvkyc0h66",
    "timestamp": 1784898096000,
    "dateString": "24/7/2026",
    "hh": "20",
    "mm": "01",
    "hall": "5",
    "type": "pet"
  },
  {
    "id": "mrylx2pzbezsgkdh36",
    "timestamp": 1784935447000,
    "dateString": "25/7/2026",
    "hh": "06",
    "mm": "24",
    "hall": "5",
    "type": "speed builder hall"
  },
  {
    "id": "mrylx2pzvsrvao7xaia",
    "timestamp": 1786082136000,
    "dateString": "7/8/2026",
    "hh": "12",
    "mm": "55",
    "hall": "4",
    "type": "normal"
  },
  {
    "id": "mrylx2pziqj00obqdm",
    "timestamp": 1784924311000,
    "dateString": "25/7/2026",
    "hh": "03",
    "mm": "18",
    "hall": "4",
    "type": "normal"
  },
  {
    "id": "mrylx2pzzolnuy3x3b",
    "timestamp": 1784928792000,
    "dateString": "25/7/2026",
    "hh": "04",
    "mm": "33",
    "hall": "4",
    "type": "normal"
  },
  {
    "id": "mrylx2pz7a1l3ggfw9g",
    "timestamp": 1784886427000,
    "dateString": "24/7/2026",
    "hh": "16",
    "mm": "47",
    "hall": "4",
    "type": "normal"
  },
  {
    "id": "mrylx2pzz4za3mh5yt9",
    "timestamp": 1784909240000,
    "dateString": "24/7/2026",
    "hh": "23",
    "mm": "07",
    "hall": "4",
    "type": "normal"
  },
  {
    "id": "mrylx2pzlm2u7e4de1s",
    "timestamp": 1784920026000,
    "dateString": "25/7/2026",
    "hh": "02",
    "mm": "07",
    "hall": "4",
    "type": "normal"
  },
  {
    "id": "mrylx2pzwqaouujo8pd",
    "timestamp": 1784967395000,
    "dateString": "25/7/2026",
    "hh": "15",
    "mm": "16",
    "hall": "4",
    "type": "normal"
  },
  {
    "id": "mrylx2pz6w2r2jnv2po",
    "timestamp": 1784993772000,
    "dateString": "25/7/2026",
    "hh": "22",
    "mm": "36",
    "hall": "4",
    "type": "builder hall"
  },
  {
    "id": "mrylx2pzmyjk2sf2c9",
    "timestamp": 1785250950000,
    "dateString": "28/7/2026",
    "hh": "22",
    "mm": "02",
    "hall": "4",
    "type": "builder hall"
  },
  {
    "id": "mrylx2pz8is2rk44ri8",
    "timestamp": 1785005386000,
    "dateString": "26/7/2026",
    "hh": "01",
    "mm": "49",
    "hall": "4",
    "type": "lab"
  },
  {
    "id": "mrylx2pz7mu1v6oy9qy",
    "timestamp": 1785067431000,
    "dateString": "26/7/2026",
    "hh": "19",
    "mm": "03",
    "hall": "4",
    "type": "lab"
  },
  {
    "id": "mrylx2pzcdm086otwkp",
    "timestamp": 1784881928000,
    "dateString": "24/7/2026",
    "hh": "15",
    "mm": "32",
    "hall": "4",
    "type": "pet"
  },
  {
    "id": "mrylx2pzq0w3ul6ybw",
    "timestamp": 1784935381000,
    "dateString": "25/7/2026",
    "hh": "06",
    "mm": "23",
    "hall": "4",
    "type": "speed builder hall"
  },
  {
    "id": "mrymscpva3k39s20pqk",
    "timestamp": 1784880638000,
    "dateString": "24/7/2026",
    "hh": "15",
    "mm": "10",
    "hall": "2",
    "type": "normal"
  },
  {
    "id": "mrymscpw9ynpdrrt5xk",
    "timestamp": 1784891045000,
    "dateString": "24/7/2026",
    "hh": "18",
    "mm": "04",
    "hall": "2",
    "type": "normal"
  },
  {
    "id": "mrymscpwvjmncv79vqj",
    "timestamp": 1784907811000,
    "dateString": "24/7/2026",
    "hh": "22",
    "mm": "43",
    "hall": "2",
    "type": "normal"
  },
  {
    "id": "mrymscpwo3cgu2wbb5",
    "timestamp": 1784900112000,
    "dateString": "24/7/2026",
    "hh": "20",
    "mm": "35",
    "hall": "2",
    "type": "normal"
  },
  {
    "id": "mrymscpwyekczv32zwa",
    "timestamp": 1784950445000,
    "dateString": "25/7/2026",
    "hh": "10",
    "mm": "34",
    "hall": "2",
    "type": "normal"
  },
  {
    "id": "mrymscpwnyps1quar7",
    "timestamp": 1784929408000,
    "dateString": "25/7/2026",
    "hh": "04",
    "mm": "43",
    "hall": "2",
    "type": "normal"
  },
  {
    "id": "mrymscpwfuz7un21x5d",
    "timestamp": 1784941805000,
    "dateString": "25/7/2026",
    "hh": "08",
    "mm": "10",
    "hall": "2",
    "type": "builder hall"
  },
  {
    "id": "mrymscpwf43jgnzjjmw",
    "timestamp": 1784913947000,
    "dateString": "25/7/2026",
    "hh": "00",
    "mm": "25",
    "hall": "2",
    "type": "builder hall"
  },
  {
    "id": "mrymscpwd4fnfcy5c9",
    "timestamp": 1785202390000,
    "dateString": "28/7/2026",
    "hh": "08",
    "mm": "33",
    "hall": "2",
    "type": "builder hall"
  },
  {
    "id": "mrymscpxnj5x8klo0b",
    "timestamp": 1784914584000,
    "dateString": "25/7/2026",
    "hh": "00",
    "mm": "36",
    "hall": "2",
    "type": "lab"
  },
  {
    "id": "mrymscpxq75ia7q1dbm",
    "timestamp": 1785052903000,
    "dateString": "26/7/2026",
    "hh": "15",
    "mm": "01",
    "hall": "2",
    "type": "lab"
  },
  {
    "id": "mrymscpx1zmpx4nhs8j",
    "timestamp": 1784934431000,
    "dateString": "25/7/2026",
    "hh": "06",
    "mm": "07",
    "hall": "2",
    "type": "pet"
  },
  {
    "id": "mrymscpxp0660dfluag",
    "timestamp": 1784935066000,
    "dateString": "25/7/2026",
    "hh": "06",
    "mm": "17",
    "hall": "2",
    "type": "speed builder hall"
  },
  {
    "id": "mryn0cn1p6teisdxhgs",
    "timestamp": 1784893814000,
    "dateString": "24/7/2026",
    "hh": "18",
    "mm": "50",
    "hall": "3",
    "type": "normal"
  },
  {
    "id": "mryn0cn12sueh5ypa0e",
    "timestamp": 1784881635000,
    "dateString": "24/7/2026",
    "hh": "15",
    "mm": "27",
    "hall": "3",
    "type": "normal"
  },
  {
    "id": "mryn0cn16mwnj29wyw",
    "timestamp": 1784880305000,
    "dateString": "24/7/2026",
    "hh": "15",
    "mm": "05",
    "hall": "3",
    "type": "normal"
  },
  {
    "id": "mryn0cn1lv6sdxd3hvi",
    "timestamp": 1784882378000,
    "dateString": "24/7/2026",
    "hh": "15",
    "mm": "39",
    "hall": "3",
    "type": "normal"
  },
  {
    "id": "mryn0cn1kbm1nay83f",
    "timestamp": 1784887583000,
    "dateString": "24/7/2026",
    "hh": "17",
    "mm": "06",
    "hall": "3",
    "type": "normal"
  },
  {
    "id": "mryn0cn1gqwssfom4g6",
    "timestamp": 1784912249000,
    "dateString": "24/7/2026",
    "hh": "23",
    "mm": "57",
    "hall": "3",
    "type": "normal"
  },
  {
    "id": "mryn0cn1xeib5cxjbn",
    "timestamp": 1785064460000,
    "dateString": "26/7/2026",
    "hh": "18",
    "mm": "14",
    "hall": "3",
    "type": "builder hall"
  },
  {
    "id": "mryn0cn1p6s6paugyg8",
    "timestamp": 1785206685000,
    "dateString": "28/7/2026",
    "hh": "09",
    "mm": "44",
    "hall": "3",
    "type": "builder hall"
  },
  {
    "id": "mryn0cn1b3m2c6l7s7f",
    "timestamp": 1784928145000,
    "dateString": "25/7/2026",
    "hh": "04",
    "mm": "22",
    "hall": "3",
    "type": "builder hall"
  },
  {
    "id": "mryn0cn2mlmdytcigrj",
    "timestamp": 1784966620000,
    "dateString": "25/7/2026",
    "hh": "15",
    "mm": "03",
    "hall": "3",
    "type": "lab"
  },
  {
    "id": "mryn0cn247ecakoacv4",
    "timestamp": 1785012224000,
    "dateString": "26/7/2026",
    "hh": "03",
    "mm": "43",
    "hall": "3",
    "type": "lab"
  },
  {
    "id": "mryn0cn2fnu7xzwa67d",
    "timestamp": 1784970026000,
    "dateString": "25/7/2026",
    "hh": "16",
    "mm": "00",
    "hall": "3",
    "type": "pet"
  },
  {
    "id": "mryn0cn2c07bsmqn9bo",
    "timestamp": 1784936921000,
    "dateString": "25/7/2026",
    "hh": "06",
    "mm": "48",
    "hall": "3",
    "type": "speed builder hall"
  },
  {
    "id": "mryn51a2yl61b8zqf29",
    "timestamp": 1784880150000,
    "dateString": "24/7/2026",
    "hh": "15",
    "mm": "02",
    "hall": "1",
    "type": "normal"
  },
  {
    "id": "mryn51a5u3qyijipza",
    "timestamp": 1784887583000,
    "dateString": "24/7/2026",
    "hh": "17",
    "mm": "06",
    "hall": "1",
    "type": "normal"
  },
  {
    "id": "mryn51a5vb2cnszp62",
    "timestamp": 1784924533000,
    "dateString": "25/7/2026",
    "hh": "03",
    "mm": "22",
    "hall": "1",
    "type": "normal"
  },
  {
    "id": "mryn51a5abk4yxknkj6",
    "timestamp": 1784904419000,
    "dateString": "24/7/2026",
    "hh": "21",
    "mm": "46",
    "hall": "1",
    "type": "normal"
  },
  {
    "id": "mryn51a5sr6005fonq",
    "timestamp": 1784921814000,
    "dateString": "25/7/2026",
    "hh": "02",
    "mm": "36",
    "hall": "1",
    "type": "normal"
  },
  {
    "id": "mryn51a5udq5lqm9l48",
    "timestamp": 1784887582000,
    "dateString": "24/7/2026",
    "hh": "17",
    "mm": "06",
    "hall": "1",
    "type": "normal"
  },
  {
    "id": "mryn51a55embx5qpz8k",
    "timestamp": 1784888160000,
    "dateString": "24/7/2026",
    "hh": "17",
    "mm": "16",
    "hall": "1",
    "type": "builder hall"
  },
  {
    "id": "mryn51a5ujm4d9h69wh",
    "timestamp": 1784889556000,
    "dateString": "24/7/2026",
    "hh": "17",
    "mm": "39",
    "hall": "1",
    "type": "builder hall"
  },
  {
    "id": "mryn51a5779jj95p9wi",
    "timestamp": 1784912373000,
    "dateString": "24/7/2026",
    "hh": "23",
    "mm": "59",
    "hall": "1",
    "type": "builder hall"
  },
  {
    "id": "mryn51a5z7es0tfco4b",
    "timestamp": 1784955802000,
    "dateString": "25/7/2026",
    "hh": "12",
    "mm": "03",
    "hall": "1",
    "type": "lab"
  },
  {
    "id": "mryn51a5i4jzwzkwla",
    "timestamp": 1784916034000,
    "dateString": "25/7/2026",
    "hh": "01",
    "mm": "00",
    "hall": "1",
    "type": "lab"
  },
  {
    "id": "mryn51a5a5d3avc8can",
    "timestamp": 1785078017000,
    "dateString": "26/7/2026",
    "hh": "22",
    "mm": "00",
    "hall": "1",
    "type": "pet"
  },
  {
    "id": "mryn51a52zg189a7gu9",
    "timestamp": 1784884150000,
    "dateString": "24/7/2026",
    "hh": "16",
    "mm": "09",
    "hall": "1",
    "type": "speed builder hall"
  }
]